tahu/__init__.py
tahu/sparkplug_b.py
tahu/sparkplug_b_pb2.py
tahu-0.1.2.dist-info/WHEEL
tahu-0.1.2.dist-info/METADATA
tahu-0.1.2.dist-info/RECORD
