Metadata-Version: 2.1
Name: tahu
Version: 0.1.2
Summary: 
Author: Aitemir Kuandyk
Author-email: mooniron.k@gmail.com
Requires-Python: >=3.8,<4.0
Classifier: License :: OSI Approved :: Eclipse Public License 2.0 (EPL-2.0)
Classifier: Programming Language :: Python :: 3
Classifier: Programming Language :: Python :: 3.10
Classifier: Programming Language :: Python :: 3.8
Classifier: Programming Language :: Python :: 3.9
Requires-Dist: protobuf (==3.19.1)
